[
{"url": "http://www.imdb.com/title/tt0111161/", "title": "The Shawshank Redemption", "rating": 9.2, "imdb_id": "tt0111161", "rank": 1, "year": 1994, "director": "Frank Darabont"},
{"url": "http://www.imdb.com/title/tt0068646/", "title": "The Godfather", "rating": 9.2, "imdb_id": "tt0068646", "rank": 2, "year": 1972, "director": "Francis Ford Coppola"},
{"url": "http://www.imdb.com/title/tt0071562/", "title": "The Godfather: Part II", "rating": 9.0, "imdb_id": "tt0071562", "rank": 3, "year": 1974, "director": "Francis Ford Coppola"},
{"url": "http://www.imdb.com/title/tt0468569/", "title": "The Dark Knight", "rating": 8.9, "imdb_id": "tt0468569", "rank": 4, "year": 2008, "director": "Christopher Nolan"},
{"url": "http://www.imdb.com/title/tt0050083/", "title": "12 Angry Men", "rating": 8.9, "imdb_id": "tt0050083", "rank": 5, "year": 1957, "director": "Sidney Lumet"},
{"url": "http://www.imdb.com/title/tt0108052/", "title": "Schindler's List", "rating": 8.9, "imdb_id": "tt0108052", "rank": 6, "year": 1993, "director": "Steven Spielberg"},
{"url": "http://www.imdb.com/title/tt0110912/", "title": "Pulp Fiction", "rating": 8.9, "imdb_id": "tt0110912", "rank": 7, "year": 1994, "director": "Quentin Tarantino"},
{"url": "http://www.imdb.com/title/tt0167260/", "title": "The Lord of the Rings: The Return of the King", "rating": 8.9, "imdb_id": "tt0167260", "rank": 8, "year": 2003, "director": "Peter Jackson"},
{"url": "http://www.imdb.com/title/tt0060196/", "title": "The Good, the Bad and the Ugly", "rating": 8.8, "imdb_id": "tt0060196", "rank": 9, "year": 1966, "director": "Sergio Leone"},
{"url": "http://www.imdb.com/title/tt0137523/", "title": "Fight Club", "rating": 8.8, "imdb_id": "tt0137523", "rank": 10, "year": 1999, "director": "David Fincher"},
{"url": "http://www.imdb.com/title/tt0120737/", "title": "The Lord of the Rings: The Fellowship of the Ring", "rating": 8.8, "imdb_id": "tt0120737", "rank": 11, "year": 2001, "director": "Peter Jackson"},
{"url": "http://www.imdb.com/title/tt0109830/", "title": "Forrest Gump", "rating": 8.7, "imdb_id": "tt0109830", "rank": 12, "year": 1994, "director": "Robert Zemeckis"},
{"url": "http://www.imdb.com/title/tt0080684/", "title": "Star Wars: Episode V - The Empire Strikes Back", "rating": 8.7, "imdb_id": "tt0080684", "rank": 13, "year": 1980, "director": "Irvin Kershner"},
{"url": "http://www.imdb.com/title/tt1375666/", "title": "Inception", "rating": 8.7, "imdb_id": "tt1375666", "rank": 14, "year": 2010, "director": "Christopher Nolan"},
{"url": "http://www.imdb.com/title/tt0167261/", "title": "The Lord of the Rings: The Two Towers", "rating": 8.7, "imdb_id": "tt0167261", "rank": 15, "year": 2002, "director": "Peter Jackson"},
{"url": "http://www.imdb.com/title/tt0073486/", "title": "One Flew Over the Cuckoo's Nest", "rating": 8.7, "imdb_id": "tt0073486", "rank": 16, "year": 1975, "director": "Milos Forman"},
{"url": "http://www.imdb.com/title/tt0099685/", "title": "Goodfellas", "rating": 8.7, "imdb_id": "tt0099685", "rank": 17, "year": 1990, "director": "Martin Scorsese"},
{"url": "http://www.imdb.com/title/tt0133093/", "title": "The Matrix", "rating": 8.7, "imdb_id": "tt0133093", "rank": 18, "year": 1999, "director": "Lana Wachowski"},
{"url": "http://www.imdb.com/title/tt0047478/", "title": "Seven Samurai", "rating": 8.6, "imdb_id": "tt0047478", "rank": 19, "year": 1954, "director": "Akira Kurosawa"},
{"url": "http://www.imdb.com/title/tt0076759/", "title": "Star Wars: Episode IV - A New Hope", "rating": 8.6, "imdb_id": "tt0076759", "rank": 20, "year": 1977, "director": "George Lucas"},
{"url": "http://www.imdb.com/title/tt0317248/", "title": "City of God", "rating": 8.6, "imdb_id": "tt0317248", "rank": 21, "year": 2002, "director": "Fernando Meirelles"},
{"url": "http://www.imdb.com/title/tt0114369/", "title": "Se7en", "rating": 8.6, "imdb_id": "tt0114369", "rank": 22, "year": 1995, "director": "David Fincher"},
{"url": "http://www.imdb.com/title/tt0102926/", "title": "The Silence of the Lambs", "rating": 8.6, "imdb_id": "tt0102926", "rank": 23, "year": 1991, "director": "Jonathan Demme"},
{"url": "http://www.imdb.com/title/tt0038650/", "title": "It's a Wonderful Life", "rating": 8.6, "imdb_id": "tt0038650", "rank": 24, "year": 1946, "director": "Frank Capra"},
{"url": "http://www.imdb.com/title/tt0118799/", "title": "Life Is Beautiful", "rating": 8.6, "imdb_id": "tt0118799", "rank": 25, "year": 1997, "director": "Roberto Benigni"},
{"url": "http://www.imdb.com/title/tt0114814/", "title": "The Usual Suspects", "rating": 8.6, "imdb_id": "tt0114814", "rank": 26, "year": 1995, "director": "Bryan Singer"},
{"url": "http://www.imdb.com/title/tt0110413/", "title": "L\u00e9on: The Professional", "rating": 8.5, "imdb_id": "tt0110413", "rank": 27, "year": 1994, "director": "Luc Besson"},
{"url": "http://www.imdb.com/title/tt0120815/", "title": "Saving Private Ryan", "rating": 8.5, "imdb_id": "tt0120815", "rank": 28, "year": 1998, "director": "Steven Spielberg"},
{"url": "http://www.imdb.com/title/tt0245429/", "title": "Spirited Away", "rating": 8.5, "imdb_id": "tt0245429", "rank": 29, "year": 2001, "director": "Hayao Miyazaki"},
{"url": "http://www.imdb.com/title/tt0064116/", "title": "Once Upon a Time in the West", "rating": 8.5, "imdb_id": "tt0064116", "rank": 30, "year": 1968, "director": "Sergio Leone"},
{"url": "http://www.imdb.com/title/tt0120586/", "title": "American History X", "rating": 8.5, "imdb_id": "tt0120586", "rank": 31, "year": 1998, "director": "Tony Kaye"},
{"url": "http://www.imdb.com/title/tt0816692/", "title": "Interstellar", "rating": 8.5, "imdb_id": "tt0816692", "rank": 32, "year": 2014, "director": "Christopher Nolan"},
{"url": "http://www.imdb.com/title/tt0054215/", "title": "Psycho", "rating": 8.5, "imdb_id": "tt0054215", "rank": 33, "year": 1960, "director": "Alfred Hitchcock"},
{"url": "http://www.imdb.com/title/tt0034583/", "title": "Casablanca", "rating": 8.5, "imdb_id": "tt0034583", "rank": 34, "year": 1942, "director": "Michael Curtiz"},
{"url": "http://www.imdb.com/title/tt0021749/", "title": "City Lights", "rating": 8.5, "imdb_id": "tt0021749", "rank": 35, "year": 1931, "director": "Charles Chaplin"},
{"url": "http://www.imdb.com/title/tt0120689/", "title": "The Green Mile", "rating": 8.5, "imdb_id": "tt0120689", "rank": 36, "year": 1999, "director": "Frank Darabont"},
{"url": "http://www.imdb.com/title/tt1675434/", "title": "The Intouchables", "rating": 8.5, "imdb_id": "tt1675434", "rank": 37, "year": 2011, "director": "Olivier Nakache"},
{"url": "http://www.imdb.com/title/tt0027977/", "title": "Modern Times", "rating": 8.5, "imdb_id": "tt0027977", "rank": 38, "year": 1936, "director": "Charles Chaplin"},
{"url": "http://www.imdb.com/title/tt0082971/", "title": "Raiders of the Lost Ark", "rating": 8.5, "imdb_id": "tt0082971", "rank": 39, "year": 1981, "director": "Steven Spielberg"},
{"url": "http://www.imdb.com/title/tt0047396/", "title": "Rear Window", "rating": 8.5, "imdb_id": "tt0047396", "rank": 40, "year": 1954, "director": "Alfred Hitchcock"},
{"url": "http://www.imdb.com/title/tt0253474/", "title": "The Pianist", "rating": 8.5, "imdb_id": "tt0253474", "rank": 41, "year": 2002, "director": "Roman Polanski"},
{"url": "http://www.imdb.com/title/tt0407887/", "title": "The Departed", "rating": 8.5, "imdb_id": "tt0407887", "rank": 42, "year": 2006, "director": "Martin Scorsese"},
{"url": "http://www.imdb.com/title/tt0103064/", "title": "Terminator 2: Judgment Day", "rating": 8.5, "imdb_id": "tt0103064", "rank": 43, "year": 1991, "director": "James Cameron"},
{"url": "http://www.imdb.com/title/tt0088763/", "title": "Back to the Future", "rating": 8.5, "imdb_id": "tt0088763", "rank": 44, "year": 1985, "director": "Robert Zemeckis"},
{"url": "http://www.imdb.com/title/tt2582802/", "title": "Whiplash", "rating": 8.5, "imdb_id": "tt2582802", "rank": 45, "year": 2014, "director": "Damien Chazelle"},
{"url": "http://www.imdb.com/title/tt0172495/", "title": "Gladiator", "rating": 8.5, "imdb_id": "tt0172495", "rank": 46, "year": 2000, "director": "Ridley Scott"},
{"url": "http://www.imdb.com/title/tt0209144/", "title": "Memento", "rating": 8.5, "imdb_id": "tt0209144", "rank": 47, "year": 2000, "director": "Christopher Nolan"},
{"url": "http://www.imdb.com/title/tt0482571/", "title": "The Prestige", "rating": 8.5, "imdb_id": "tt0482571", "rank": 48, "year": 2006, "director": "Christopher Nolan"},
{"url": "http://www.imdb.com/title/tt0110357/", "title": "The Lion King", "rating": 8.5, "imdb_id": "tt0110357", "rank": 49, "year": 1994, "director": "Roger Allers"},
{"url": "http://www.imdb.com/title/tt0078788/", "title": "Apocalypse Now", "rating": 8.5, "imdb_id": "tt0078788", "rank": 50, "year": 1979, "director": "Francis Ford Coppola"},
{"url": "http://www.imdb.com/title/tt0078748/", "title": "Alien", "rating": 8.4, "imdb_id": "tt0078748", "rank": 51, "year": 1979, "director": "Ridley Scott"},
{"url": "http://www.imdb.com/title/tt0043014/", "title": "Sunset Boulevard", "rating": 8.4, "imdb_id": "tt0043014", "rank": 52, "year": 1950, "director": "Billy Wilder"},
{"url": "http://www.imdb.com/title/tt0032553/", "title": "The Great Dictator", "rating": 8.4, "imdb_id": "tt0032553", "rank": 53, "year": 1940, "director": "Charles Chaplin"},
{"url": "http://www.imdb.com/title/tt0057012/", "title": "Dr. Strangelove or: How I Learned to Stop Worrying and Love the Bomb", "rating": 8.4, "imdb_id": "tt0057012", "rank": 54, "year": 1964, "director": "Stanley Kubrick"},
{"url": "http://www.imdb.com/title/tt0095765/", "title": "Cinema Paradiso", "rating": 8.4, "imdb_id": "tt0095765", "rank": 55, "year": 1988, "director": "Giuseppe Tornatore"},
{"url": "http://www.imdb.com/title/tt0405094/", "title": "The Lives of Others", "rating": 8.4, "imdb_id": "tt0405094", "rank": 56, "year": 2006, "director": "Florian Henckel von Donnersmarck"},
{"url": "http://www.imdb.com/title/tt0095327/", "title": "Grave of the Fireflies", "rating": 8.4, "imdb_id": "tt0095327", "rank": 57, "year": 1988, "director": "Isao Takahata"},
{"url": "http://www.imdb.com/title/tt0050825/", "title": "Paths of Glory", "rating": 8.4, "imdb_id": "tt0050825", "rank": 58, "year": 1957, "director": "Stanley Kubrick"},
{"url": "http://www.imdb.com/title/tt1853728/", "title": "Django Unchained", "rating": 8.4, "imdb_id": "tt1853728", "rank": 59, "year": 2012, "director": "Quentin Tarantino"},
{"url": "http://www.imdb.com/title/tt0081505/", "title": "The Shining", "rating": 8.4, "imdb_id": "tt0081505", "rank": 60, "year": 1980, "director": "Stanley Kubrick"},
{"url": "http://www.imdb.com/title/tt0910970/", "title": "WALL\u00b7E", "rating": 8.4, "imdb_id": "tt0910970", "rank": 61, "year": 2008, "director": "Andrew Stanton"},
{"url": "http://www.imdb.com/title/tt0169547/", "title": "American Beauty", "rating": 8.4, "imdb_id": "tt0169547", "rank": 62, "year": 1999, "director": "Sam Mendes"},
{"url": "http://www.imdb.com/title/tt1345836/", "title": "The Dark Knight Rises", "rating": 8.4, "imdb_id": "tt1345836", "rank": 63, "year": 2012, "director": "Christopher Nolan"},
{"url": "http://www.imdb.com/title/tt0119698/", "title": "Princess Mononoke", "rating": 8.4, "imdb_id": "tt0119698", "rank": 64, "year": 1997, "director": "Hayao Miyazaki"},
{"url": "http://www.imdb.com/title/tt0090605/", "title": "Aliens", "rating": 8.4, "imdb_id": "tt0090605", "rank": 65, "year": 1986, "director": "James Cameron"},
{"url": "http://www.imdb.com/title/tt0364569/", "title": "Oldboy", "rating": 8.4, "imdb_id": "tt0364569", "rank": 66, "year": 2003, "director": "Chan-wook Park"},
{"url": "http://www.imdb.com/title/tt0087843/", "title": "Once Upon a Time in America", "rating": 8.4, "imdb_id": "tt0087843", "rank": 67, "year": 1984, "director": "Sergio Leone"},
{"url": "http://www.imdb.com/title/tt0051201/", "title": "Witness for the Prosecution", "rating": 8.3, "imdb_id": "tt0051201", "rank": 68, "year": 1957, "director": "Billy Wilder"},
{"url": "http://www.imdb.com/title/tt0082096/", "title": "Das Boot", "rating": 8.3, "imdb_id": "tt0082096", "rank": 69, "year": 1981, "director": "Wolfgang Petersen"},
{"url": "http://www.imdb.com/title/tt0033467/", "title": "Citizen Kane", "rating": 8.3, "imdb_id": "tt0033467", "rank": 70, "year": 1941, "director": "Orson Welles"},
{"url": "http://www.imdb.com/title/tt5074352/", "title": "Dangal", "rating": 8.3, "imdb_id": "tt5074352", "rank": 71, "year": 2016, "director": "Nitesh Tiwari"},
{"url": "http://www.imdb.com/title/tt0052357/", "title": "Vertigo", "rating": 8.3, "imdb_id": "tt0052357", "rank": 72, "year": 1958, "director": "Alfred Hitchcock"},
{"url": "http://www.imdb.com/title/tt0053125/", "title": "North by Northwest", "rating": 8.3, "imdb_id": "tt0053125", "rank": 73, "year": 1959, "director": "Alfred Hitchcock"},
{"url": "http://www.imdb.com/title/tt0086190/", "title": "Star Wars: Episode VI - Return of the Jedi", "rating": 8.3, "imdb_id": "tt0086190", "rank": 74, "year": 1983, "director": "Richard Marquand"},
{"url": "http://www.imdb.com/title/tt0105236/", "title": "Reservoir Dogs", "rating": 8.3, "imdb_id": "tt0105236", "rank": 75, "year": 1992, "director": "Quentin Tarantino"},
{"url": "http://www.imdb.com/title/tt0112573/", "title": "Braveheart", "rating": 8.3, "imdb_id": "tt0112573", "rank": 76, "year": 1995, "director": "Mel Gibson"},
{"url": "http://www.imdb.com/title/tt0022100/", "title": "M", "rating": 8.3, "imdb_id": "tt0022100", "rank": 77, "year": 1931, "director": "Fritz Lang"},
{"url": "http://www.imdb.com/title/tt0180093/", "title": "Requiem for a Dream", "rating": 8.3, "imdb_id": "tt0180093", "rank": 78, "year": 2000, "director": "Darren Aronofsky"},
{"url": "http://www.imdb.com/title/tt0211915/", "title": "Am\u00e9lie", "rating": 8.3, "imdb_id": "tt0211915", "rank": 79, "year": 2001, "director": "Jean-Pierre Jeunet"},
{"url": "http://www.imdb.com/title/tt0986264/", "title": "Like Stars on Earth", "rating": 8.3, "imdb_id": "tt0986264", "rank": 80, "year": 2007, "director": "Aamir Khan"},
{"url": "http://www.imdb.com/title/tt0066921/", "title": "A Clockwork Orange", "rating": 8.3, "imdb_id": "tt0066921", "rank": 81, "year": 1971, "director": "Stanley Kubrick"},
{"url": "http://www.imdb.com/title/tt0056172/", "title": "Lawrence of Arabia", "rating": 8.3, "imdb_id": "tt0056172", "rank": 82, "year": 1962, "director": "David Lean"},
{"url": "http://www.imdb.com/title/tt0075314/", "title": "Taxi Driver", "rating": 8.3, "imdb_id": "tt0075314", "rank": 83, "year": 1976, "director": "Martin Scorsese"},
{"url": "http://www.imdb.com/title/tt0036775/", "title": "Double Indemnity", "rating": 8.3, "imdb_id": "tt0036775", "rank": 84, "year": 1944, "director": "Billy Wilder"},
{"url": "http://www.imdb.com/title/tt0338013/", "title": "Eternal Sunshine of the Spotless Mind", "rating": 8.3, "imdb_id": "tt0338013", "rank": 85, "year": 2004, "director": "Michel Gondry"},
{"url": "http://www.imdb.com/title/tt0086879/", "title": "Amadeus", "rating": 8.3, "imdb_id": "tt0086879", "rank": 86, "year": 1984, "director": "Milos Forman"},
{"url": "http://www.imdb.com/title/tt0056592/", "title": "To Kill a Mockingbird", "rating": 8.3, "imdb_id": "tt0056592", "rank": 87, "year": 1962, "director": "Robert Mulligan"},
{"url": "http://www.imdb.com/title/tt0435761/", "title": "Toy Story 3", "rating": 8.3, "imdb_id": "tt0435761", "rank": 88, "year": 2010, "director": "Lee Unkrich"},
{"url": "http://www.imdb.com/title/tt0093058/", "title": "Full Metal Jacket", "rating": 8.3, "imdb_id": "tt0093058", "rank": 89, "year": 1987, "director": "Stanley Kubrick"},
{"url": "http://www.imdb.com/title/tt0062622/", "title": "2001: A Space Odyssey", "rating": 8.3, "imdb_id": "tt0062622", "rank": 90, "year": 1968, "director": "Stanley Kubrick"},
{"url": "http://www.imdb.com/title/tt0045152/", "title": "Singin' in the Rain", "rating": 8.3, "imdb_id": "tt0045152", "rank": 91, "year": 1952, "director": "Stanley Donen"},
{"url": "http://www.imdb.com/title/tt0070735/", "title": "The Sting", "rating": 8.3, "imdb_id": "tt0070735", "rank": 92, "year": 1973, "director": "George Roy Hill"},
{"url": "http://www.imdb.com/title/tt5311514/", "title": "Your Name", "rating": 8.3, "imdb_id": "tt5311514", "rank": 93, "year": 2016, "director": "Makoto Shinkai"},
{"url": "http://www.imdb.com/title/tt0114709/", "title": "Toy Story", "rating": 8.3, "imdb_id": "tt0114709", "rank": 94, "year": 1995, "director": "John Lasseter"},
{"url": "http://www.imdb.com/title/tt0040522/", "title": "Bicycle Thieves", "rating": 8.3, "imdb_id": "tt0040522", "rank": 95, "year": 1948, "director": "Vittorio De Sica"},
{"url": "http://www.imdb.com/title/tt0012349/", "title": "The Kid", "rating": 8.3, "imdb_id": "tt0012349", "rank": 96, "year": 1921, "director": "Charles Chaplin"},
{"url": "http://www.imdb.com/title/tt0361748/", "title": "Inglourious Basterds", "rating": 8.3, "imdb_id": "tt0361748", "rank": 97, "year": 2009, "director": "Quentin Tarantino"},
{"url": "http://www.imdb.com/title/tt1187043/", "title": "3 Idiots", "rating": 8.3, "imdb_id": "tt1187043", "rank": 98, "year": 2009, "director": "Rajkumar Hirani"},
{"url": "http://www.imdb.com/title/tt0208092/", "title": "Snatch", "rating": 8.3, "imdb_id": "tt0208092", "rank": 99, "year": 2000, "director": "Guy Ritchie"},
{"url": "http://www.imdb.com/title/tt0071853/", "title": "Monty Python and the Holy Grail", "rating": 8.3, "imdb_id": "tt0071853", "rank": 100, "year": 1975, "director": "Terry Gilliam"},
{"url": "http://www.imdb.com/title/tt0119488/", "title": "L.A. Confidential", "rating": 8.3, "imdb_id": "tt0119488", "rank": 101, "year": 1997, "director": "Curtis Hanson"},
{"url": "http://www.imdb.com/title/tt0059578/", "title": "For a Few Dollars More", "rating": 8.3, "imdb_id": "tt0059578", "rank": 102, "year": 1965, "director": "Sergio Leone"},
{"url": "http://www.imdb.com/title/tt0476735/", "title": "My Father and My Son", "rating": 8.3, "imdb_id": "tt0476735", "rank": 103, "year": 2005, "director": "\u00c7agan Irmak"},
{"url": "http://www.imdb.com/title/tt2106476/", "title": "The Hunt", "rating": 8.3, "imdb_id": "tt2106476", "rank": 104, "year": 2012, "director": "Thomas Vinterberg"},
{"url": "http://www.imdb.com/title/tt0086250/", "title": "Scarface", "rating": 8.3, "imdb_id": "tt0086250", "rank": 105, "year": 1983, "director": "Brian De Palma"},
{"url": "http://www.imdb.com/title/tt0119217/", "title": "Good Will Hunting", "rating": 8.3, "imdb_id": "tt0119217", "rank": 106, "year": 1997, "director": "Gus Van Sant"},
{"url": "http://www.imdb.com/title/tt0053604/", "title": "The Apartment", "rating": 8.2, "imdb_id": "tt0053604", "rank": 107, "year": 1960, "director": "Billy Wilder"},
{"url": "http://www.imdb.com/title/tt0042876/", "title": "Rashomon", "rating": 8.2, "imdb_id": "tt0042876", "rank": 108, "year": 1950, "director": "Akira Kurosawa"},
{"url": "http://www.imdb.com/title/tt1832382/", "title": "A Separation", "rating": 8.2, "imdb_id": "tt1832382", "rank": 109, "year": 2011, "director": "Asghar Farhadi"},
{"url": "http://www.imdb.com/title/tt0017136/", "title": "Metropolis", "rating": 8.2, "imdb_id": "tt0017136", "rank": 110, "year": 1927, "director": "Fritz Lang"},
{"url": "http://www.imdb.com/title/tt0097576/", "title": "Indiana Jones and the Last Crusade", "rating": 8.2, "imdb_id": "tt0097576", "rank": 111, "year": 1989, "director": "Steven Spielberg"},
{"url": "http://www.imdb.com/title/tt0042192/", "title": "All About Eve", "rating": 8.2, "imdb_id": "tt0042192", "rank": 112, "year": 1950, "director": "Joseph L. Mankiewicz"},
{"url": "http://www.imdb.com/title/tt0055630/", "title": "Yojimbo", "rating": 8.2, "imdb_id": "tt0055630", "rank": 113, "year": 1961, "director": "Akira Kurosawa"},
{"url": "http://www.imdb.com/title/tt0372784/", "title": "Batman Begins", "rating": 8.2, "imdb_id": "tt0372784", "rank": 114, "year": 2005, "director": "Christopher Nolan"},
{"url": "http://www.imdb.com/title/tt1049413/", "title": "Up", "rating": 8.2, "imdb_id": "tt1049413", "rank": 115, "year": 2009, "director": "Pete Docter"},
{"url": "http://www.imdb.com/title/tt0053291/", "title": "Some Like It Hot", "rating": 8.2, "imdb_id": "tt0053291", "rank": 116, "year": 1959, "director": "Billy Wilder"},
{"url": "http://www.imdb.com/title/tt0040897/", "title": "The Treasure of the Sierra Madre", "rating": 8.2, "imdb_id": "tt0040897", "rank": 117, "year": 1948, "director": "John Huston"},
{"url": "http://www.imdb.com/title/tt0105695/", "title": "Unforgiven", "rating": 8.2, "imdb_id": "tt0105695", "rank": 118, "year": 1992, "director": "Clint Eastwood"},
{"url": "http://www.imdb.com/title/tt0363163/", "title": "Downfall", "rating": 8.2, "imdb_id": "tt0363163", "rank": 119, "year": 2004, "director": "Oliver Hirschbiegel"},
{"url": "http://www.imdb.com/title/tt0081398/", "title": "Raging Bull", "rating": 8.2, "imdb_id": "tt0081398", "rank": 120, "year": 1980, "director": "Martin Scorsese"},
{"url": "http://www.imdb.com/title/tt0095016/", "title": "Die Hard", "rating": 8.2, "imdb_id": "tt0095016", "rank": 121, "year": 1988, "director": "John McTiernan"},
{"url": "http://www.imdb.com/title/tt0118849/", "title": "Children of Heaven", "rating": 8.2, "imdb_id": "tt0118849", "rank": 122, "year": 1997, "director": "Majid Majidi"},
{"url": "http://www.imdb.com/title/tt0041959/", "title": "The Third Man", "rating": 8.2, "imdb_id": "tt0041959", "rank": 123, "year": 1949, "director": "Carol Reed"},
{"url": "http://www.imdb.com/title/tt0113277/", "title": "Heat", "rating": 8.2, "imdb_id": "tt0113277", "rank": 124, "year": 1995, "director": "Michael Mann"},
{"url": "http://www.imdb.com/title/tt0057115/", "title": "The Great Escape", "rating": 8.2, "imdb_id": "tt0057115", "rank": 125, "year": 1963, "director": "John Sturges"},
{"url": "http://www.imdb.com/title/tt0071315/", "title": "Chinatown", "rating": 8.2, "imdb_id": "tt0071315", "rank": 126, "year": 1974, "director": "Roman Polanski"},
{"url": "http://www.imdb.com/title/tt0044741/", "title": "Ikiru", "rating": 8.2, "imdb_id": "tt0044741", "rank": 127, "year": 1952, "director": "Akira Kurosawa"},
{"url": "http://www.imdb.com/title/tt3890160/", "title": "Baby Driver", "rating": 8.2, "imdb_id": "tt3890160", "rank": 128, "year": 2017, "director": "Edgar Wright"},
{"url": "http://www.imdb.com/title/tt0457430/", "title": "Pan's Labyrinth", "rating": 8.2, "imdb_id": "tt0457430", "rank": 129, "year": 2006, "director": "Guillermo del Toro"},
{"url": "http://www.imdb.com/title/tt0096283/", "title": "My Neighbor Totoro", "rating": 8.2, "imdb_id": "tt0096283", "rank": 130, "year": 1988, "director": "Hayao Miyazaki"},
{"url": "http://www.imdb.com/title/tt2096673/", "title": "Inside Out", "rating": 8.2, "imdb_id": "tt2096673", "rank": 131, "year": 2015, "director": "Pete Docter"},
{"url": "http://www.imdb.com/title/tt0089881/", "title": "Ran", "rating": 8.2, "imdb_id": "tt0089881", "rank": 132, "year": 1985, "director": "Akira Kurosawa"},
{"url": "http://www.imdb.com/title/tt0015864/", "title": "The Gold Rush", "rating": 8.2, "imdb_id": "tt0015864", "rank": 133, "year": 1925, "director": "Charles Chaplin"},
{"url": "http://www.imdb.com/title/tt3783958/", "title": "La La Land", "rating": 8.2, "imdb_id": "tt3783958", "rank": 134, "year": 2016, "director": "Damien Chazelle"},
{"url": "http://www.imdb.com/title/tt1305806/", "title": "The Secret in Their Eyes", "rating": 8.2, "imdb_id": "tt1305806", "rank": 135, "year": 2009, "director": "Juan Jos\u00e9 Campanella"},
{"url": "http://www.imdb.com/title/tt0047296/", "title": "On the Waterfront", "rating": 8.2, "imdb_id": "tt0047296", "rank": 136, "year": 1954, "director": "Elia Kazan"},
{"url": "http://www.imdb.com/title/tt3170832/", "title": "Room", "rating": 8.2, "imdb_id": "tt3170832", "rank": 137, "year": 2015, "director": "Lenny Abrahamson"},
{"url": "http://www.imdb.com/title/tt0050212/", "title": "The Bridge on the River Kwai", "rating": 8.2, "imdb_id": "tt0050212", "rank": 138, "year": 1957, "director": "David Lean"},
{"url": "http://www.imdb.com/title/tt0347149/", "title": "Howl's Moving Castle", "rating": 8.2, "imdb_id": "tt0347149", "rank": 139, "year": 2004, "director": "Hayao Miyazaki"},
{"url": "http://www.imdb.com/title/tt0083658/", "title": "Blade Runner", "rating": 8.2, "imdb_id": "tt0083658", "rank": 140, "year": 1982, "director": "Ridley Scott"},
{"url": "http://www.imdb.com/title/tt1255953/", "title": "Incendies", "rating": 8.2, "imdb_id": "tt1255953", "rank": 141, "year": 2010, "director": "Denis Villeneuve"},
{"url": "http://www.imdb.com/title/tt0055031/", "title": "Judgment at Nuremberg", "rating": 8.2, "imdb_id": "tt0055031", "rank": 142, "year": 1961, "director": "Stanley Kramer"},
{"url": "http://www.imdb.com/title/tt0050976/", "title": "The Seventh Seal", "rating": 8.2, "imdb_id": "tt0050976", "rank": 143, "year": 1957, "director": "Ingmar Bergman"},
{"url": "http://www.imdb.com/title/tt0120735/", "title": "Lock, Stock and Two Smoking Barrels", "rating": 8.2, "imdb_id": "tt0120735", "rank": 144, "year": 1998, "director": "Guy Ritchie"},
{"url": "http://www.imdb.com/title/tt0031679/", "title": "Mr. Smith Goes to Washington", "rating": 8.2, "imdb_id": "tt0031679", "rank": 145, "year": 1939, "director": "Frank Capra"},
{"url": "http://www.imdb.com/title/tt3315342/", "title": "Logan", "rating": 8.2, "imdb_id": "tt3315342", "rank": 146, "year": 2017, "director": "James Mangold"},
{"url": "http://www.imdb.com/title/tt0112641/", "title": "Casino", "rating": 8.2, "imdb_id": "tt0112641", "rank": 147, "year": 1995, "director": "Martin Scorsese"},
{"url": "http://www.imdb.com/title/tt0268978/", "title": "A Beautiful Mind", "rating": 8.2, "imdb_id": "tt0268978", "rank": 148, "year": 2001, "director": "Ron Howard"},
{"url": "http://www.imdb.com/title/tt0060107/", "title": "Andrei Rublev", "rating": 8.2, "imdb_id": "tt0060107", "rank": 149, "year": 1966, "director": "Andrei Tarkovsky"},
{"url": "http://www.imdb.com/title/tt0080678/", "title": "The Elephant Man", "rating": 8.1, "imdb_id": "tt0080678", "rank": 150, "year": 1980, "director": "David Lynch"},
{"url": "http://www.imdb.com/title/tt0050986/", "title": "Wild Strawberries", "rating": 8.1, "imdb_id": "tt0050986", "rank": 151, "year": 1957, "director": "Ingmar Bergman"},
{"url": "http://www.imdb.com/title/tt0434409/", "title": "V for Vendetta", "rating": 8.1, "imdb_id": "tt0434409", "rank": 152, "year": 2005, "director": "James McTeigue"},
{"url": "http://www.imdb.com/title/tt0017925/", "title": "The General", "rating": 8.1, "imdb_id": "tt0017925", "rank": 153, "year": 1926, "director": "Clyde Bruckman"},
{"url": "http://www.imdb.com/title/tt0993846/", "title": "The Wolf of Wall Street", "rating": 8.1, "imdb_id": "tt0993846", "rank": 154, "year": 2013, "director": "Martin Scorsese"},
{"url": "http://www.imdb.com/title/tt1291584/", "title": "Warrior", "rating": 8.1, "imdb_id": "tt1291584", "rank": 155, "year": 2011, "director": "Gavin O'Connor"},
{"url": "http://www.imdb.com/title/tt0116231/", "title": "The Bandit", "rating": 8.1, "imdb_id": "tt0116231", "rank": 156, "year": 1996, "director": "Yavuz Turgul"},
{"url": "http://www.imdb.com/title/tt0117951/", "title": "Trainspotting", "rating": 8.1, "imdb_id": "tt0117951", "rank": 157, "year": 1996, "director": "Danny Boyle"},
{"url": "http://www.imdb.com/title/tt0018455/", "title": "Sunrise", "rating": 8.1, "imdb_id": "tt0018455", "rank": 158, "year": 1927, "director": "F.W. Murnau"},
{"url": "http://www.imdb.com/title/tt0046912/", "title": "Dial M for Murder", "rating": 8.1, "imdb_id": "tt0046912", "rank": 159, "year": 1954, "director": "Alfred Hitchcock"},
{"url": "http://www.imdb.com/title/tt1205489/", "title": "Gran Torino", "rating": 8.1, "imdb_id": "tt1205489", "rank": 160, "year": 2008, "director": "Clint Eastwood"},
{"url": "http://www.imdb.com/title/tt2119532/", "title": "Hacksaw Ridge", "rating": 8.1, "imdb_id": "tt2119532", "rank": 161, "year": 2016, "director": "Mel Gibson"},
{"url": "http://www.imdb.com/title/tt0077416/", "title": "The Deer Hunter", "rating": 8.1, "imdb_id": "tt0077416", "rank": 162, "year": 1978, "director": "Michael Cimino"},
{"url": "http://www.imdb.com/title/tt0031381/", "title": "Gone with the Wind", "rating": 8.1, "imdb_id": "tt0031381", "rank": 163, "year": 1939, "director": "Victor Fleming"},
{"url": "http://www.imdb.com/title/tt0116282/", "title": "Fargo", "rating": 8.1, "imdb_id": "tt0116282", "rank": 164, "year": 1996, "director": "Joel Coen"},
{"url": "http://www.imdb.com/title/tt0118715/", "title": "The Big Lebowski", "rating": 8.1, "imdb_id": "tt0118715", "rank": 165, "year": 1998, "director": "Joel Coen"},
{"url": "http://www.imdb.com/title/tt0167404/", "title": "The Sixth Sense", "rating": 8.1, "imdb_id": "tt0167404", "rank": 166, "year": 1999, "director": "M. Night Shyamalan"},
{"url": "http://www.imdb.com/title/tt0084787/", "title": "The Thing", "rating": 8.1, "imdb_id": "tt0084787", "rank": 167, "year": 1982, "director": "John Carpenter"},
{"url": "http://www.imdb.com/title/tt0266543/", "title": "Finding Nemo", "rating": 8.1, "imdb_id": "tt0266543", "rank": 168, "year": 2003, "director": "Andrew Stanton"},
{"url": "http://www.imdb.com/title/tt0046438/", "title": "Tokyo Story", "rating": 8.1, "imdb_id": "tt0046438", "rank": 169, "year": 1953, "director": "Yasujir\u00f4 Ozu"},
{"url": "http://www.imdb.com/title/tt0477348/", "title": "No Country for Old Men", "rating": 8.1, "imdb_id": "tt0477348", "rank": 170, "year": 2007, "director": "Ethan Coen"},
{"url": "http://www.imdb.com/title/tt0405508/", "title": "Rang De Basanti", "rating": 8.1, "imdb_id": "tt0405508", "rank": 171, "year": 2006, "director": "Rakeysh Omprakash Mehra"},
{"url": "http://www.imdb.com/title/tt0019254/", "title": "The Passion of Joan of Arc", "rating": 8.1, "imdb_id": "tt0019254", "rank": 172, "year": 1928, "director": "Carl Theodor Dreyer"},
{"url": "http://www.imdb.com/title/tt0061512/", "title": "Cool Hand Luke", "rating": 8.1, "imdb_id": "tt0061512", "rank": 173, "year": 1967, "director": "Stuart Rosenberg"},
{"url": "http://www.imdb.com/title/tt0032976/", "title": "Rebecca", "rating": 8.1, "imdb_id": "tt0032976", "rank": 174, "year": 1940, "director": "Alfred Hitchcock"},
{"url": "http://www.imdb.com/title/tt1280558/", "title": "A Wednesday", "rating": 8.1, "imdb_id": "tt1280558", "rank": 175, "year": 2008, "director": "Neeraj Pandey"},
{"url": "http://www.imdb.com/title/tt0469494/", "title": "There Will Be Blood", "rating": 8.1, "imdb_id": "tt0469494", "rank": 176, "year": 2007, "director": "Paul Thomas Anderson"},
{"url": "http://www.imdb.com/title/tt0892769/", "title": "How to Train Your Dragon", "rating": 8.1, "imdb_id": "tt0892769", "rank": 177, "year": 2010, "director": "Dean DeBlois"},
{"url": "http://www.imdb.com/title/tt0266697/", "title": "Kill Bill: Vol. 1", "rating": 8.1, "imdb_id": "tt0266697", "rank": 178, "year": 2003, "director": "Quentin Tarantino"},
{"url": "http://www.imdb.com/title/tt0091251/", "title": "Come and See", "rating": 8.1, "imdb_id": "tt0091251", "rank": 179, "year": 1985, "director": "Elem Klimov"},
{"url": "http://www.imdb.com/title/tt0978762/", "title": "Mary and Max", "rating": 8.1, "imdb_id": "tt0978762", "rank": 180, "year": 2009, "director": "Adam Elliot"},
{"url": "http://www.imdb.com/title/tt2267998/", "title": "Gone Girl", "rating": 8.1, "imdb_id": "tt2267998", "rank": 181, "year": 2014, "director": "David Fincher"},
{"url": "http://www.imdb.com/title/tt0758758/", "title": "Into the Wild", "rating": 8.1, "imdb_id": "tt0758758", "rank": 182, "year": 2007, "director": "Sean Penn"},
{"url": "http://www.imdb.com/title/tt0025316/", "title": "It Happened One Night", "rating": 8.1, "imdb_id": "tt0025316", "rank": 183, "year": 1934, "director": "Frank Capra"},
{"url": "http://www.imdb.com/title/tt1130884/", "title": "Shutter Island", "rating": 8.1, "imdb_id": "tt1130884", "rank": 184, "year": 2010, "director": "Martin Scorsese"},
{"url": "http://www.imdb.com/title/tt0079470/", "title": "Life of Brian", "rating": 8.1, "imdb_id": "tt0079470", "rank": 185, "year": 1979, "director": "Terry Jones"},
{"url": "http://www.imdb.com/title/tt0091763/", "title": "Platoon", "rating": 8.1, "imdb_id": "tt0091763", "rank": 186, "year": 1986, "director": "Oliver Stone"},
{"url": "http://www.imdb.com/title/tt3011894/", "title": "Wild Tales", "rating": 8.1, "imdb_id": "tt3011894", "rank": 187, "year": 2014, "director": "Dami\u00e1n Szifron"},
{"url": "http://www.imdb.com/title/tt0395169/", "title": "Hotel Rwanda", "rating": 8.1, "imdb_id": "tt0395169", "rank": 188, "year": 2004, "director": "Terry George"},
{"url": "http://www.imdb.com/title/tt1979320/", "title": "Rush", "rating": 8.1, "imdb_id": "tt1979320", "rank": 189, "year": 2013, "director": "Ron Howard"},
{"url": "http://www.imdb.com/title/tt0046268/", "title": "The Wages of Fear", "rating": 8.1, "imdb_id": "tt0046268", "rank": 190, "year": 1953, "director": "Henri-Georges Clouzot"},
{"url": "http://www.imdb.com/title/tt0074958/", "title": "Network", "rating": 8.1, "imdb_id": "tt0074958", "rank": 191, "year": 1976, "director": "Sidney Lumet"},
{"url": "http://www.imdb.com/title/tt0107207/", "title": "In the Name of the Father", "rating": 8.1, "imdb_id": "tt0107207", "rank": 192, "year": 1993, "director": "Jim Sheridan"},
{"url": "http://www.imdb.com/title/tt0092005/", "title": "Stand by Me", "rating": 8.1, "imdb_id": "tt0092005", "rank": 193, "year": 1986, "director": "Rob Reiner"},
{"url": "http://www.imdb.com/title/tt0053198/", "title": "The 400 Blows", "rating": 8.1, "imdb_id": "tt0053198", "rank": 194, "year": 1959, "director": "Fran\u00e7ois Truffaut"},
{"url": "http://www.imdb.com/title/tt0052618/", "title": "Ben-Hur", "rating": 8.1, "imdb_id": "tt0052618", "rank": 195, "year": 1959, "director": "William Wyler"},
{"url": "http://www.imdb.com/title/tt2278388/", "title": "The Grand Budapest Hotel", "rating": 8.1, "imdb_id": "tt2278388", "rank": 196, "year": 2014, "director": "Wes Anderson"},
{"url": "http://www.imdb.com/title/tt1392190/", "title": "Mad Max: Fury Road", "rating": 8.1, "imdb_id": "tt1392190", "rank": 197, "year": 2015, "director": "George Miller"},
{"url": "http://www.imdb.com/title/tt1895587/", "title": "Spotlight", "rating": 8.1, "imdb_id": "tt1895587", "rank": 198, "year": 2015, "director": "Tom McCarthy"},
{"url": "http://www.imdb.com/title/tt2024544/", "title": "12 Years a Slave", "rating": 8.1, "imdb_id": "tt2024544", "rank": 199, "year": 2013, "director": "Steve McQueen"},
{"url": "http://www.imdb.com/title/tt0060827/", "title": "Persona", "rating": 8.1, "imdb_id": "tt0060827", "rank": 200, "year": 1966, "director": "Ingmar Bergman"},
{"url": "http://www.imdb.com/title/tt0405159/", "title": "Million Dollar Baby", "rating": 8.1, "imdb_id": "tt0405159", "rank": 201, "year": 2004, "director": "Clint Eastwood"},
{"url": "http://www.imdb.com/title/tt0064115/", "title": "Butch Cassidy and the Sundance Kid", "rating": 8.1, "imdb_id": "tt0064115", "rank": 202, "year": 1969, "director": "George Roy Hill"},
{"url": "http://www.imdb.com/title/tt0107290/", "title": "Jurassic Park", "rating": 8.1, "imdb_id": "tt0107290", "rank": 203, "year": 1993, "director": "Steven Spielberg"},
{"url": "http://www.imdb.com/title/tt0353969/", "title": "Memories of Murder", "rating": 8.1, "imdb_id": "tt0353969", "rank": 204, "year": 2003, "director": "Joon-ho Bong"},
{"url": "http://www.imdb.com/title/tt0245712/", "title": "Amores Perros", "rating": 8.1, "imdb_id": "tt0245712", "rank": 205, "year": 2000, "director": "Alejandro Gonz\u00e1lez I\u00f1\u00e1rritu"},
{"url": "http://www.imdb.com/title/tt0374887/", "title": "Munna Bhai M.B.B.S.", "rating": 8.1, "imdb_id": "tt0374887", "rank": 206, "year": 2003, "director": "Rajkumar Hirani"},
{"url": "http://www.imdb.com/title/tt0033870/", "title": "The Maltese Falcon", "rating": 8.1, "imdb_id": "tt0033870", "rank": 207, "year": 1941, "director": "John Huston"},
{"url": "http://www.imdb.com/title/tt0079944/", "title": "Stalker", "rating": 8.1, "imdb_id": "tt0079944", "rank": 208, "year": 1979, "director": "Andrei Tarkovsky"},
{"url": "http://www.imdb.com/title/tt0050783/", "title": "The Nights of Cabiria", "rating": 8.1, "imdb_id": "tt0050783", "rank": 209, "year": 1957, "director": "Federico Fellini"},
{"url": "http://www.imdb.com/title/tt0120382/", "title": "The Truman Show", "rating": 8.1, "imdb_id": "tt0120382", "rank": 210, "year": 1998, "director": "Peter Weir"},
{"url": "http://www.imdb.com/title/tt0093779/", "title": "The Princess Bride", "rating": 8.1, "imdb_id": "tt0093779", "rank": 211, "year": 1987, "director": "Rob Reiner"},
{"url": "http://www.imdb.com/title/tt1028532/", "title": "Hachi: A Dog's Tale", "rating": 8.1, "imdb_id": "tt1028532", "rank": 212, "year": 2009, "director": "Lasse Hallstr\u00f6m"},
{"url": "http://www.imdb.com/title/tt0087544/", "title": "Nausica\u00e4 of the Valley of the Wind", "rating": 8.1, "imdb_id": "tt0087544", "rank": 213, "year": 1984, "director": "Hayao Miyazaki"},
{"url": "http://www.imdb.com/title/tt0112471/", "title": "Before Sunrise", "rating": 8.0, "imdb_id": "tt0112471", "rank": 214, "year": 1995, "director": "Richard Linklater"},
{"url": "http://www.imdb.com/title/tt0073707/", "title": "Sholay", "rating": 8.0, "imdb_id": "tt0073707", "rank": 215, "year": 1975, "director": "Ramesh Sippy"},
{"url": "http://www.imdb.com/title/tt2488496/", "title": "Star Wars: The Force Awakens", "rating": 8.0, "imdb_id": "tt2488496", "rank": 216, "year": 2015, "director": "J.J. Abrams"},
{"url": "http://www.imdb.com/title/tt0032551/", "title": "The Grapes of Wrath", "rating": 8.0, "imdb_id": "tt0032551", "rank": 217, "year": 1940, "director": "John Ford"},
{"url": "http://www.imdb.com/title/tt1201607/", "title": "Harry Potter and the Deathly Hallows: Part 2", "rating": 8.0, "imdb_id": "tt1201607", "rank": 218, "year": 2011, "director": "David Yates"},
{"url": "http://www.imdb.com/title/tt0075148/", "title": "Rocky", "rating": 8.0, "imdb_id": "tt0075148", "rank": 219, "year": 1976, "director": "John G. Avildsen"},
{"url": "http://www.imdb.com/title/tt0052311/", "title": "Touch of Evil", "rating": 8.0, "imdb_id": "tt0052311", "rank": 220, "year": 1958, "director": "Orson Welles"},
{"url": "http://www.imdb.com/title/tt1392214/", "title": "Prisoners", "rating": 8.0, "imdb_id": "tt1392214", "rank": 221, "year": 2013, "director": "Denis Villeneuve"},
{"url": "http://www.imdb.com/title/tt0083987/", "title": "Gandhi", "rating": 8.0, "imdb_id": "tt0083987", "rank": 222, "year": 1982, "director": "Richard Attenborough"},
{"url": "http://www.imdb.com/title/tt0046911/", "title": "Diabolique", "rating": 8.0, "imdb_id": "tt0046911", "rank": 223, "year": 1955, "director": "Henri-Georges Clouzot"},
{"url": "http://www.imdb.com/title/tt0075686/", "title": "Annie Hall", "rating": 8.0, "imdb_id": "tt0075686", "rank": 224, "year": 1977, "director": "Woody Allen"},
{"url": "http://www.imdb.com/title/tt0264464/", "title": "Catch Me If You Can", "rating": 8.0, "imdb_id": "tt0264464", "rank": 225, "year": 2002, "director": "Steven Spielberg"},
{"url": "http://www.imdb.com/title/tt0246578/", "title": "Donnie Darko", "rating": 8.0, "imdb_id": "tt0246578", "rank": 226, "year": 2001, "director": "Richard Kelly"},
{"url": "http://www.imdb.com/title/tt0242519/", "title": "Hera Pheri", "rating": 8.0, "imdb_id": "tt0242519", "rank": 227, "year": 2000, "director": "Priyadarshan"},
{"url": "http://www.imdb.com/title/tt0198781/", "title": "Monsters, Inc.", "rating": 8.0, "imdb_id": "tt0198781", "rank": 228, "year": 2001, "director": "Pete Docter"},
{"url": "http://www.imdb.com/title/tt0440963/", "title": "The Bourne Ultimatum", "rating": 8.0, "imdb_id": "tt0440963", "rank": 229, "year": 2007, "director": "Paul Greengrass"},
{"url": "http://www.imdb.com/title/tt0088247/", "title": "The Terminator", "rating": 8.0, "imdb_id": "tt0088247", "rank": 230, "year": 1984, "director": "James Cameron"},
{"url": "http://www.imdb.com/title/tt0056801/", "title": "8\u00bd", "rating": 8.0, "imdb_id": "tt0056801", "rank": 231, "year": 1963, "director": "Federico Fellini"},
{"url": "http://www.imdb.com/title/tt0032138/", "title": "The Wizard of Oz", "rating": 8.0, "imdb_id": "tt0032138", "rank": 232, "year": 1939, "director": "Victor Fleming"},
{"url": "http://www.imdb.com/title/tt0107048/", "title": "Groundhog Day", "rating": 8.0, "imdb_id": "tt0107048", "rank": 233, "year": 1993, "director": "Harold Ramis"},
{"url": "http://www.imdb.com/title/tt0072684/", "title": "Barry Lyndon", "rating": 8.0, "imdb_id": "tt0072684", "rank": 234, "year": 1975, "director": "Stanley Kubrick"},
{"url": "http://www.imdb.com/title/tt0113247/", "title": "La Haine", "rating": 8.0, "imdb_id": "tt0113247", "rank": 235, "year": 1995, "director": "Mathieu Kassovitz"},
{"url": "http://www.imdb.com/title/tt0114746/", "title": "Twelve Monkeys", "rating": 8.0, "imdb_id": "tt0114746", "rank": 236, "year": 1995, "director": "Terry Gilliam"},
{"url": "http://www.imdb.com/title/tt0073195/", "title": "Jaws", "rating": 8.0, "imdb_id": "tt0073195", "rank": 237, "year": 1975, "director": "Steven Spielberg"},
{"url": "http://www.imdb.com/title/tt0338564/", "title": "Infernal Affairs", "rating": 8.0, "imdb_id": "tt0338564", "rank": 238, "year": 2002, "director": "Wai-Keung Lau"},
{"url": "http://www.imdb.com/title/tt0036868/", "title": "The Best Years of Our Lives", "rating": 8.0, "imdb_id": "tt0036868", "rank": 239, "year": 1946, "director": "William Wyler"},
{"url": "http://www.imdb.com/title/tt1954470/", "title": "Gangs of Wasseypur", "rating": 8.0, "imdb_id": "tt1954470", "rank": 240, "year": 2012, "director": "Anurag Kashyap"},
{"url": "http://www.imdb.com/title/tt1454029/", "title": "The Help", "rating": 8.0, "imdb_id": "tt1454029", "rank": 241, "year": 2011, "director": "Tate Taylor"},
{"url": "http://www.imdb.com/title/tt0101414/", "title": "Beauty and the Beast", "rating": 8.0, "imdb_id": "tt0101414", "rank": 242, "year": 1991, "director": "Gary Trousdale"},
{"url": "http://www.imdb.com/title/tt0058946/", "title": "The Battle of Algiers", "rating": 8.0, "imdb_id": "tt0058946", "rank": 243, "year": 1966, "director": "Gillo Pontecorvo"},
{"url": "http://www.imdb.com/title/tt0072890/", "title": "Dog Day Afternoon", "rating": 8.0, "imdb_id": "tt0072890", "rank": 244, "year": 1975, "director": "Sidney Lumet"},
{"url": "http://www.imdb.com/title/tt0118694/", "title": "In the Mood for Love", "rating": 8.0, "imdb_id": "tt0118694", "rank": 245, "year": 2000, "director": "Kar-Wai Wong"},
{"url": "http://www.imdb.com/title/tt0325980/", "title": "Pirates of the Caribbean: The Curse of the Black Pearl", "rating": 8.0, "imdb_id": "tt0325980", "rank": 246, "year": 2003, "director": "Gore Verbinski"},
{"url": "http://www.imdb.com/title/tt0056687/", "title": "What Ever Happened to Baby Jane?", "rating": 8.0, "imdb_id": "tt0056687", "rank": 247, "year": 1962, "director": "Robert Aldrich"},
{"url": "http://www.imdb.com/title/tt0087884/", "title": "Paris, Texas", "rating": 8.0, "imdb_id": "tt0087884", "rank": 248, "year": 1984, "director": "Wim Wenders"},
{"url": "http://www.imdb.com/title/tt2338151/", "title": "PK", "rating": 8.0, "imdb_id": "tt2338151", "rank": 249, "year": 2014, "director": "Rajkumar Hirani"},
{"url": "http://www.imdb.com/title/tt0169102/", "title": "Lagaan: Once Upon a Time in India", "rating": 8.0, "imdb_id": "tt0169102", "rank": 250, "year": 2001, "director": "Ashutosh Gowariker"},
{"average rating": 8.261999999999974}
]